rpm_inspector_rpm/__init__.py
rpm_inspector_rpm/bin/rpm
rpm_inspector_rpm/bin/rpmrc
rpm_inspector_rpm/licenses/CHANGES
rpm_inspector_rpm/licenses/COPYING
rpm_inspector_rpm/licenses/CREDITS
rpm_inspector_rpm/licenses/INSTALL
rpm_inspector_rpm/licenses/README
rpm_inspector_rpm/licenses/rpm.8
rpm_inspector_rpm/licenses/rpmdb.8
rpm_inspector_rpm-4.16.1.3.210404.dist-info/METADATA
rpm_inspector_rpm-4.16.1.3.210404.dist-info/README.rst
rpm_inspector_rpm-4.16.1.3.210404.dist-info/WHEEL
rpm_inspector_rpm-4.16.1.3.210404.dist-info/apache-2.0.LICENSE
rpm_inspector_rpm-4.16.1.3.210404.dist-info/entry_points.txt
rpm_inspector_rpm-4.16.1.3.210404.dist-info/gpl-2.0.LICENSE
rpm_inspector_rpm-4.16.1.3.210404.dist-info/lgpl-2.0.LICENSE
rpm_inspector_rpm-4.16.1.3.210404.dist-info/rpm-inspector-rpm.ABOUT
rpm_inspector_rpm-4.16.1.3.210404.dist-info/rpm.ABOUT
rpm_inspector_rpm-4.16.1.3.210404.dist-info/rpm.NOTICE
rpm_inspector_rpm-4.16.1.3.210404.dist-info/top_level.txt
rpm_inspector_rpm-4.16.1.3.210404.dist-info/RECORD
