Metadata-Version: 1.1
Name: rpm-inspector-rpm
Version: 4.16.1.3.210404
Summary: A ScanCode path provider plugin to provide a prebuilt native rpm binary built with many rpm backend database formats supported. The rpm binary is built from sources that are bundled in the repo and sdist.
Home-page: https://github.com/nexB/scancode-plugins
Author: nexB
Author-email: info@aboutcode.org
License:  apache-2.0 AND (gpl-2.0 AND lgpl-2.0)
Keywords: open source,packagedcode,scancode,rpm,rpmdb
Platform: UNKNOWN
Classifier: Development Status :: 5 - Production/Stable
Classifier: Intended Audience :: Developers
Classifier: Topic :: Utilities
